dtx/__init__.py
dtx/cli/__init__.py
dtx/cli/agents_builder_cli.py
dtx/cli/attacks.py
dtx/cli/check_dep.py
dtx/cli/cli.py
dtx/cli/console_output.py
dtx/cli/datasetargs.py
dtx/cli/docker_cli.py
dtx/cli/env_manager.py
dtx/cli/evaluatorargs.py
dtx/cli/format.py
dtx/cli/model_provider_cli.py
dtx/cli/mutation_cli.py
dtx/cli/planner.py
dtx/cli/providers.py
dtx/cli/runner.py
dtx/cli/scoping.py
dtx/cli/validatorsargs.py
dtx/cli/workspace.py
dtx/config/__init__.py
dtx/config/globals.py
dtx/config/hf_models.yml
dtx/config/providers.py
dtx/core/__init__.py
dtx/core/base/__init__.py
dtx/core/base/evaluator.py
dtx/core/builders/__init__.py
dtx/core/builders/provider_vars.py
dtx/core/builders/redteam.py
dtx/core/converters/__init__.py
dtx/core/converters/prompts.py
dtx/core/converters/providers/__init__.py
dtx/core/engine/__init__.py
dtx/core/engine/evaluator.py
dtx/core/engine/scanner.py
dtx/core/exceptions/__init__.py
dtx/core/exceptions/agents.py
dtx/core/exceptions/base.py
dtx/core/exceptions/evaluator.py
dtx/core/logging.py
dtx/core/reports/__init__.py
dtx/core/reports/html/__init__.py
dtx/core/reports/html/builder.py
dtx/core/reports/html/generator.py
dtx/core/reports/templates/html_report_template.html
dtx/env.template
dtx/experimental/__init__.py
dtx/experimental/generate_risks.py
dtx/plugins/__init__.py
dtx/plugins/agents/__init__.py
dtx/plugins/agents/autogen/__init__.py
dtx/plugins/agents/autogen/agents_scope_generator.py
dtx/plugins/agents/autogen/utils/__init__.py
dtx/plugins/agents/autogen/utils/console.py
dtx/plugins/classification/__init__.py
dtx/plugins/classification/adversarial_prompts.py
dtx/plugins/classification/toxigen.py
dtx/plugins/prompts/__init__.py
dtx/plugins/prompts/app/__init__.py
dtx/plugins/prompts/app/cli.py
dtx/plugins/prompts/langhub/__init__.py
dtx/plugins/prompts/langhub/cli.py
dtx/plugins/prompts/langhub/lh_client.py
dtx/plugins/prompts/template/__init__.py
dtx/plugins/prompts/template/resolver.py
dtx/plugins/providers/__init__.py
dtx-0.34.0.dist-info/METADATA
dtx-0.34.0.dist-info/WHEEL
dtx-0.34.0.dist-info/entry_points.txt
dtx-0.34.0.dist-info/RECORD
