Metadata-Version: 2.3
Name: dtx
Version: 0.34.0
Summary: AI Red Teaming Tool and Framework
Author: developer
Author-email: research@detoxio.ai
Requires-Python: >=3.11,<3.14
Classifier: Programming Language :: Python :: 3
Classifier: Programming Language :: Python :: 3.11
Classifier: Programming Language :: Python :: 3.12
Classifier: Programming Language :: Python :: 3.13
Provides-Extra: torch
Requires-Dist: aiofiles (>=24.1.0,<25.0.0)
Requires-Dist: base2048 (>=0.1.3,<0.2.0)
Requires-Dist: datasets (>=3.3.2,<4.0.0)
Requires-Dist: deprecated (>=1.2.18,<2.0.0)
Requires-Dist: deprecation (>=2.1.0,<3.0.0)
Requires-Dist: detoxify (>=0.5.2,<0.6.0) ; extra == "torch"
Requires-Dist: docker (>=7.1.0,<8.0.0)
Requires-Dist: dotenv (>=0.9.9,<0.10.0)
Requires-Dist: dtx-attacks (>=0.4.0,<0.5.0)
Requires-Dist: dtx-models (>=0.43.0,<0.44.0)
Requires-Dist: ecoji (>=0.1.1,<0.2.0)
Requires-Dist: faiss-cpu (>=1.11.0,<2.0.0)
Requires-Dist: gradio-client (>=1.8.0,<2.0.0)
Requires-Dist: haralyzer (>=2.4.0,<3.0.0)
Requires-Dist: httptools (>=0.6.4,<0.7.0)
Requires-Dist: huggingface-hub[hf-xet] (>=0.31.2,<0.32.0)
Requires-Dist: jinja2 (>=3.1.6,<4.0.0)
Requires-Dist: jq (>=1.8.0,<2.0.0)
Requires-Dist: langchain (>=0.3.18,<0.4.0)
Requires-Dist: langchain-openai (>=0.3.5,<0.4.0)
Requires-Dist: langgraph (>=0.3.30,<0.4.0)
Requires-Dist: litellm[proxy] (>=1.63.6,<2.0.0)
Requires-Dist: loguru (>=0.7.3,<0.8.0)
Requires-Dist: markitdown (>=0.0.2,<0.0.3)
Requires-Dist: numpy (>=2.2.5,<3.0.0)
Requires-Dist: ollama (>=0.5.1)
Requires-Dist: playwright (>=1.51.0,<2.0.0)
Requires-Dist: pydantic (>=2.10.6,<3.0.0)
Requires-Dist: pydantic-yaml (>=1.4.0,<2.0.0)
Requires-Dist: python-dotenv (>=1.0.1,<2.0.0)
Requires-Dist: pyyaml (>=6.0.2,<7.0.0)
Requires-Dist: retry (>=0.9.2,<0.10.0)
Requires-Dist: rich (>=13.9.4,<14.0.0)
Requires-Dist: sentence-transformers (>=4.1.0,<5.0.0) ; extra == "torch"
Requires-Dist: tenacity (>=9.1.2,<10.0.0)
Requires-Dist: tiktoken (>=0.8.0,<0.9.0)
Requires-Dist: torch (>=2.6.0,<3.0.0) ; extra == "torch"
Requires-Dist: transformers (>=4.49.0,<5.0.0) ; extra == "torch"
Requires-Dist: validators (>=0.34.0,<0.35.0)
Requires-Dist: zalgolib (>=0.2.2,<0.3.0)
